{
  "Human Swarm Unit": {
    "alias": ["กีกี้", "ฝูงกีกี้", "ทหาร"],
    "description": "ยูนิตทหารราบจำนวนมากของฝ่ายมนุษย์ (เช่น Astra Militarum Conscripts, Cultists) ที่มีความสามารถในการต่อสู้รายบุคคลต่ำ แต่มีจำนวนมากพอที่จะกดดันศัตรู, ยึด Objective หรือเป็นโล่กำบัง",
    "M": "6\"",
    "T": "3",
    "SV": "5+",
    "W": "1",
    "LD": "7+",
    "OC": "2"
  },
  "Skitarii Swarm Unit": {
    "alias": ["กีกี้", "ฝูงกีกี้", "ranger"],
    "description": "ยูนิตทหารราบจำนวนมากของ Adeptus Mechanicus Skitarii (เช่น Skitarii Vanguards/Rangers) ที่มีความสามารถในการต่อสู้รายบุคคลต่ำ แต่มีจำนวนมากพอที่จะกดดันศัตรูหรือยึด Objective",
    "M": "6\"",
    "T": "3",
    "SV": "4+",
    "W": "1",
    "LD": "7+",
    "OC": "2",
    "invulnerable_save": "5+"
  },
  "Space Marines Unit": {
    "alias": ["มาลีน", "พาวเวอร์อาร์เมอร์", "มาลีนจั้มแผก"],
    "description": "ยูนิตทหารราบมาตรฐานของ Space Marines สวม Power Armour ซึ่งให้ความทนทานและประสิทธิภาพการต่อสู้ที่สมดุล เป็นกำลังหลักของกองทัพ",
    "M": "6\"",
    "T": "4",
    "SV": "3+",
    "W": "2",
    "LD": "7+",
    "OC": "2"
  },
  "Space Marines Terminator Unit": {
    "alias": ["เทอมี่", "มาลีนเทอมี่", "เทอร์มิเนเตอร์"],
    "description": "ยูนิตทหารราบหนักของ Space Marines สวม Terminator Armour ที่ให้การป้องกันสูงสุดและมีอาวุธทรงพลัง เหมาะสำหรับแนวหน้าหรือการเข้าตีเป้าหมายสำคัญ",
    "M": "5\"",
    "T": "5",
    "SV": "2+",
    "W": "3",
    "LD": "7+",
    "OC": "1",
    "invulnerable_save": "4+"
  },
  "Space Marines Scout Unit": {
    "alias": ["สเก้าท์มาลีน", "มาลีนสอดแนม"],
    "description": "ยูนิตทหารราบเบาของ Space Marines ที่เน้นการสอดแนม, การเคลื่อนที่เร็ว และการยึด Objective ล่วงหน้า มักจะไม่สวม Power Armour เต็มรูปแบบ",
    "M": "6\"",
    "T": "4",
    "SV": "4+",
    "W": "2",
    "LD": "7+",
    "OC": "1"
  },
  "Space Marines Gravis Unit": {
    "alias": ["มาลีนกราวิส", "กราวิสอาร์เมอร์"],
    "description": "ยูนิตทหารราบหนักของ Space Marines สวม Gravis Armour ที่ให้ความทนทานสูงกว่า Power Armour มาตรฐานและมักจะมีอาวุธระยะใกล้หรือระยะกลางที่ทรงพลัง",
    "M": "6\"",
    "T": "6",
    "SV": "3+",
    "W": "3",
    "LD": "7+",
    "OC": "2"
  },
  "Human Elite Unit": {
    "alias": ["อิมกาดอีลีท", "หน่วยรบพิเศษอิมกาด"],
    "description": "หน่วยรบพิเศษหรือทหารราบที่มีประสบการณ์ของ Astra Militarum (เช่น Kasrkin, Scions) ที่มีความสามารถในการต่อสู้และอุปกรณ์ที่ดีกว่าทหารราบมาตรฐาน",
    "M": "6\"",
    "T": "3",
    "SV": "4+",
    "W": "1",
    "LD": "7+",
    "OC": "1"
  },
  "Skitarii Elite Unit": {
    "alias": ["สคิทาริอีลีท", "หน่วยรบพิเศษสคิทาริ", "นินจา", "ไก่เล็ก", "ค้างคาว"],
    "description": "หน่วยรบเฉพาะทางหรือทหารราบที่มีประสิทธิภาพสูงของ Adeptus Mechanicus Skitarii (เช่น Sicarian Ruststalkers/Infiltrators, Serberys Raiders) ที่เน้นความเร็ว, การโจมตีเฉพาะทาง หรือการรบประชิด",
    "M": "9\"",
    "T": "4",
    "SV": "4+",
    "W": "2",
    "LD": "7+",
    "OC": "1",
    "invulnerable_save": "5+"
  },
  "Dedicated Transport": {
    "alias": ["รถขนคน"],
    "description": "ยานพาหนะที่ใช้ขนส่งยูนิต Infantry เป็นหลัก มีความสามารถในการต่อสู้จำกัด แต่เน้นความทนทานและการเคลื่อนที่เพื่อนำทัพเข้าสู่จุดยุทธศาสตร์",
    "T": "9",
    "SV": "3+"
  },
  "Small Tank": {
    "alias": ["รถถังเล็ก"],
    "description": "ยานพาหนะหุ้มเกราะขนาดเล็กถึงกลาง มีบทบาทได้หลากหลายทั้งสนับสนุนการยิงหรือโจมตีแนวหน้า มีความคล่องตัวสูงกว่ารถถังขนาดใหญ่",
    "T": "7",
    "SV": "3+"
  },
  "Medium Tank": {
    "alias": ["รถถังกลาง"],
    "description": "ยานพาหนะหุ้มเกราะขนาดกลาง มักจะมีอาวุธที่หลากหลายและทนทานกว่ารถถังเล็ก เหมาะสำหรับภารกิจสนับสนุนการยิงหรือเป็นกำลังหลักในแนวหน้า",
    "T": "10",
    "SV": "3+"
  },
  "Heavy Tank": {
    "alias": ["รถถังใหญ่"],
    "description": "ยานพาหนะหุ้มเกราะขนาดใหญ่และมีอาวุธหนักเป็นพิเศษ ใช้ในการเจาะแนวรับศัตรูหรือโจมตีเป้าหมายสำคัญ มีความทนทานสูงมาก",
    "T": "12",
    "SV": "2+"
  }
}